udnn/__init__.py
udnn/model.py
udnn/trainer.py
udnn/upscaler.py
udnn/utils/__init__.py
udnn/utils/dataloader.py
udnn/utils/logger.py
udnn/utils/merge.py
udnn/utils/timer.py
udnn-0.0.3.dist-info/LICENSE
udnn-0.0.3.dist-info/METADATA
udnn-0.0.3.dist-info/WHEEL
udnn-0.0.3.dist-info/top_level.txt
udnn-0.0.3.dist-info/RECORD
