Metadata-Version: 2.1
Name: udnn
Version: 0.0.3
Summary: UDNN
Home-page: https://github.com/DimitriosBellos/UDNN
Author: Dimitrios Bellos
Author-email: Dimitrios.Bellos@nottingham.ac.uk
License: UNKNOWN
Platform: UNKNOWN
Classifier: Programming Language :: Python :: 3
Classifier: License :: OSI Approved :: Apache Software License
Requires-Python: >=3.6.4
License-File: LICENSE
Requires-Dist: numpy
Requires-Dist: pillow
Requires-Dist: pytorch (>=0.4)
Requires-Dist: h5py
